JaiShriRam/__init__.py
JaiShriRam/module.py
JaiShriRam-0.0.2.dist-info/LICENSE.txt
JaiShriRam-0.0.2.dist-info/METADATA
JaiShriRam-0.0.2.dist-info/WHEEL
JaiShriRam-0.0.2.dist-info/top_level.txt
JaiShriRam-0.0.2.dist-info/RECORD
